seleniumlogin/__init__.py
seleniumlogin/settings_test.py
seleniumlogin/urls.py
test_/__init__.py
test_/urls.py
test_/views.py
django_selenium_login-2.0.0.dist-info/LICENSE
django_selenium_login-2.0.0.dist-info/METADATA
django_selenium_login-2.0.0.dist-info/WHEEL
django_selenium_login-2.0.0.dist-info/top_level.txt
django_selenium_login-2.0.0.dist-info/RECORD
