Metadata-Version: 1.1
Name: django-selenium-login
Version: 2.0.0
Summary: A quick login for selenium tests to be used in Django projects
Home-page: https://github.com/feffe/django-selenium-login
Author: Fredrik Westermark
Author-email: feffe.westermark@gmail.com
License: MIT
Keywords: selenium django login
Platform: UNKNOWN
Classifier: Development Status :: 5 - Production/Stable
Classifier: Topic :: Software Development :: Quality Assurance
Classifier: Intended Audience :: Developers
Classifier: License :: OSI Approved :: MIT License
